alas_ce0/__init__.py
alas_ce0/clients/__init__.py
alas_ce0/clients/api_client.py
alas_ce0/clients/core.py
alas_ce0/common/__init__.py
alas_ce0/common/client_base.py
alas_ce0/delivery/__init__.py
alas_ce0/delivery/b2c.py
alas_ce0/delivery/delivery_order.py
alas_ce0/integration/__init__.py
alas_ce0/integration/device_magic.py
alas_ce0/integration/shipper.py
alas_ce0/integration/whatsapp.py
alas_ce0/management/__init__.py
alas_ce0/management/barcode.py
alas_ce0/management/bulk.py
alas_ce0/management/configuration.py
alas_ce0/management/contact.py
alas_ce0/management/cross_docking.py
alas_ce0/management/dairy.py
alas_ce0/management/delivery_entity.py
alas_ce0/management/distribution_zone.py
alas_ce0/management/employee.py
alas_ce0/management/feature.py
alas_ce0/management/geographic_coverage.py
alas_ce0/management/geographic_coverage_active.py
alas_ce0/management/maintenance.py
alas_ce0/management/notification.py
alas_ce0/management/package_template.py
alas_ce0/management/packaging.py
alas_ce0/management/pallet.py
alas_ce0/management/polygon.py
alas_ce0/management/position.py
alas_ce0/management/product_template.py
alas_ce0/management/resource.py
alas_ce0/management/role.py
alas_ce0/management/roles_group.py
alas_ce0/management/service_level.py
alas_ce0/management/shelf.py
alas_ce0/management/task.py
alas_ce0/management/user.py
alas_ce0/management/user_app.py
alas_ce0/management/vehicle.py
alas_ce0/reporting/__init__.py
alas_ce0/reporting/operational_report.py
alas_ce0/reporting/regional_partner_report.py
alas_ce0/reporting/report.py
alas_ce0/reporting/report_manager.py
alas_ce0/scheduling/__init__.py
alas_ce0/scheduling/route.py
alas_ce0/task/__init__.py
alas_ce0/task/data_job.py
alas_ce0_client-5.8.5.dist-info/licenses/LICENSE.txt
alas_ce0_client-5.8.5.dist-info/METADATA
alas_ce0_client-5.8.5.dist-info/WHEEL
alas_ce0_client-5.8.5.dist-info/top_level.txt
alas_ce0_client-5.8.5.dist-info/RECORD
